LICENSE
README.md
pytest_execution_timer/__init__.py
pytest_execution_timer/plugin.py
pytest_execution_timer-0.1.0.dist-info/entry_points.txt
pytest_execution_timer-0.1.0.dist-info/LICENSE
pytest_execution_timer-0.1.0.dist-info/WHEEL
pytest_execution_timer-0.1.0.dist-info/METADATA
pytest_execution_timer-0.1.0.dist-info/RECORD
