Metadata-Version: 2.1
Name: pytest-execution-timer
Version: 0.1.0
Summary: A timer for the phases of Pytest's execution.
Home-page: https://pypi.org/project/pytest-execution-timer/
License: MIT
Author: Mike Fiedler
Author-email: miketheman@gmail.com
Requires-Python: >=3.7,<4.0
Classifier: Development Status :: 4 - Beta
Classifier: Framework :: Pytest
Classifier: Intended Audience :: Developers
Classifier: License :: OSI Approved :: MIT License
Classifier: Operating System :: OS Independent
Classifier: Programming Language :: Python
Classifier: Programming Language :: Python :: 3
Classifier: Programming Language :: Python :: 3.10
Classifier: Programming Language :: Python :: 3.7
Classifier: Programming Language :: Python :: 3.8
Classifier: Programming Language :: Python :: 3.9
Classifier: Programming Language :: Python :: Implementation :: CPython
Classifier: Topic :: Software Development :: Testing
Project-URL: Bug Tracker, https://github.com/miketheman/pytest-execution-timer/issues
Project-URL: Repository, https://github.com/miketheman/pytest-execution-timer
